blind_watermark/__init__.py
blind_watermark/access.py
blind_watermark/att.py
blind_watermark/blind_watermark.py
blind_watermark/cli_tools.py
blind_watermark/pool.py
blind_watermark/tools.py
text_blind_watermark_p-1.2.4.dist-info/METADATA
text_blind_watermark_p-1.2.4.dist-info/WHEEL
text_blind_watermark_p-1.2.4.dist-info/top_level.txt
text_blind_watermark_p-1.2.4.dist-info/RECORD
