Metadata-Version: 2.1
Name: text-blind-watermark-p
Version: 1.2.4
Summary: Text Blind Watermark in Python
Home-page: https://github.com/guofei9987/text_blind_watermark_private
Author: Guo Fei
Author-email: guofei9987@foxmail.com
License: MIT
Platform: linux
Platform: windows
Platform: macos
Requires-Python: >=3.5
Requires-Dist: pycryptodome
